qualsynth/__init__.py
qualsynth/generator.py
qualsynth/baselines/__init__.py
qualsynth/baselines/ctgan_baseline.py
qualsynth/baselines/smote.py
qualsynth/baselines/tabfairgdt.py
qualsynth/core/__init__.py
qualsynth/core/iterative_workflow.py
qualsynth/data/__init__.py
qualsynth/data/eda.py
qualsynth/data/preprocessing.py
qualsynth/data/splitting.py
qualsynth/evaluation/__init__.py
qualsynth/evaluation/classifiers.py
qualsynth/evaluation/fairness.py
qualsynth/evaluation/metrics.py
qualsynth/experiments/__init__.py
qualsynth/experiments/experiment_runner.py
qualsynth/generators/__init__.py
qualsynth/generators/counterfactual_generator.py
qualsynth/modules/__init__.py
qualsynth/modules/dataset_profiler.py
qualsynth/modules/diversity_planner.py
qualsynth/modules/fairness_auditor.py
qualsynth/modules/fairness_reauditor.py
qualsynth/modules/optimizer.py
qualsynth/modules/schema_profiler.py
qualsynth/modules/validator.py
qualsynth/prompts/__init__.py
qualsynth/prompts/base_templates.py
qualsynth/prompts/constraint_encoder.py
qualsynth/prompts/counterfactual_templates.py
qualsynth/prompts/fairness_templates.py
qualsynth/prompts/few_shot_builder.py
qualsynth/prompts/prompt_builder.py
qualsynth/utils/__init__.py
qualsynth/utils/adaptive_iteration_predictor.py
qualsynth/utils/config_loader.py
qualsynth/utils/diversity_maximizer.py
qualsynth/utils/experiment_logger.py
qualsynth/utils/llm_config.py
qualsynth/utils/sota_duplicate_prevention.py
qualsynth/utils/value_transformer.py
qualsynth/validation/__init__.py
qualsynth/validation/adaptive_validator.py
qualsynth/validation/universal_validator.py
qualsynth-1.0.0.dist-info/METADATA
qualsynth-1.0.0.dist-info/WHEEL
qualsynth-1.0.0.dist-info/top_level.txt
qualsynth-1.0.0.dist-info/RECORD
