Metadata-Version: 2.4
Name: qualsynth
Version: 1.0.0
Summary: Quality-Driven Synthetic Data Generation via LLM-Guided Oversampling
Author-email: Asim Sinan Yuksel <asimyuksel@sdu.edu.tr>
Maintainer-email: Asim Sinan Yuksel <asimyuksel@sdu.edu.tr>
License: MIT
Project-URL: Homepage, https://github.com/asimyuksel/qualsynth
Project-URL: Documentation, https://github.com/asimyuksel/qualsynth#readme
Project-URL: Repository, https://github.com/asimyuksel/qualsynth
Project-URL: Issues, https://github.com/asimyuksel/qualsynth/issues
Project-URL: Changelog, https://github.com/asimyuksel/qualsynth/releases
Keywords: synthetic data,oversampling,imbalanced learning,large language models,LLM,data augmentation,machine learning,quality validation,tabular data
Classifier: Development Status :: 4 - Beta
Classifier: Intended Audience :: Science/Research
Classifier: Intended Audience :: Developers
Classifier: License :: OSI Approved :: MIT License
Classifier: Operating System :: OS Independent
Classifier: Programming Language :: Python :: 3
Classifier: Programming Language :: Python :: 3.8
Classifier: Programming Language :: Python :: 3.9
Classifier: Programming Language :: Python :: 3.10
Classifier: Programming Language :: Python :: 3.11
Classifier: Programming Language :: Python :: 3.12
Classifier: Topic :: Scientific/Engineering :: Artificial Intelligence
Classifier: Topic :: Scientific/Engineering :: Information Analysis
Requires-Python: >=3.8
Requires-Dist: pandas>=1.3.0
Requires-Dist: numpy>=1.20.0
Requires-Dist: scikit-learn>=1.3.0
Requires-Dist: imbalanced-learn>=0.10.0
Requires-Dist: xgboost>=1.5.0
Requires-Dist: openai>=1.0.0
Requires-Dist: pyyaml>=6.0
Requires-Dist: tqdm>=4.60.0
Requires-Dist: scipy>=1.7.0
Requires-Dist: python-dotenv>=0.19.0
Requires-Dist: fairlearn>=0.8.0
Provides-Extra: dev
Requires-Dist: pytest>=7.0.0; extra == "dev"
Requires-Dist: pytest-cov>=4.0.0; extra == "dev"
Requires-Dist: black>=23.0.0; extra == "dev"
Requires-Dist: flake8>=6.0.0; extra == "dev"
Requires-Dist: mypy>=1.0.0; extra == "dev"
Provides-Extra: baselines
Requires-Dist: ctgan>=0.7.0; extra == "baselines"
Requires-Dist: sdv>=1.0.0; extra == "baselines"
Provides-Extra: all
Requires-Dist: qualsynth[baselines,dev]; extra == "all"
